LICENSE
MANIFEST.in
README.md
pyproject.toml
setup.cfg
setup.py
src/djangolin/__init__.py
src/djangolin/apps.py
src/djangolin/middlewares.py
src/djangolin/models.py
src/djangolin.egg-info/PKG-INFO
src/djangolin.egg-info/SOURCES.txt
src/djangolin.egg-info/dependency_links.txt
src/djangolin.egg-info/requires.txt
src/djangolin.egg-info/top_level.txt
src/djangolin/migrations/0001_initial.py
src/djangolin/migrations/__init__.py
src/djangolin/repo/__init__.py
src/djangolin/repo/middlewares/__create_logger.py
src/djangolin/repo/middlewares/__init__.py
src/djangolin/repo/models/__init__.py
src/djangolin/repo/models/__log.py
src/djangolin/repo/models/__request.py
src/djangolin/repo/models/__request_property.py
src/djangolin/repo/models/__response.py
src/djangolin/repo/models/__response_property.py
src/djangolin/repo/tools/__init__.py
src/djangolin/repo/tools/loggers/__create_instance.py
src/djangolin/repo/tools/loggers/__init__.py
src/djangolin/repo/tools/loggers/__logger.py