Metadata-Version: 2.1
Name: djangolin
Version: 0.1.0
Summary: A logger to log everything that starts with a request and ends with a response.
Home-page: https://github.com/navidsoleymani/pangolin.git
Author: Hydra
Author-email: navidsoleymani@ymail.com
License: UNKNOWN
Project-URL: Documentation, https://github.com/navidsoleymani/pangolin.git
Project-URL: Bug Reports, https://github.com/navidsoleymani/pangolin.git/issues
Project-URL: Source Code, https://github.com/navidsoleymani/pangolin.git
Keywords: logger,django
Platform: UNKNOWN
Classifier: Framework :: Django :: 4.2
Classifier: Development Status :: 5 - Production/Stable
Classifier: Intended Audience :: Developers
Classifier: Topic :: Software Development :: Build Tools
Classifier: Programming Language :: Python :: 3.8
Classifier: Programming Language :: Python :: 3.9
Classifier: Programming Language :: Python :: 3 :: Only
Classifier: License :: OSI Approved :: MIT License
Classifier: Operating System :: OS Independent
Requires-Python: >=3.8
License-File: LICENSE
